doc2pdf/__init__.py
doc2pdf/cli.py
doc2pdf/converter.py
test_convert_doc_docx_2pdf-0.2.0.dist-info/licenses/LICENSE
test_convert_doc_docx_2pdf-0.2.0.dist-info/METADATA
test_convert_doc_docx_2pdf-0.2.0.dist-info/WHEEL
test_convert_doc_docx_2pdf-0.2.0.dist-info/entry_points.txt
test_convert_doc_docx_2pdf-0.2.0.dist-info/top_level.txt
test_convert_doc_docx_2pdf-0.2.0.dist-info/RECORD
