Metadata-Version: 2.4
Name: test-convert-doc-docx-2pdf
Version: 0.2.0
Summary: Convert Microsoft Word documents (.doc, .docx) to PDF format
Author: Swati
Author-email: swati@mixorg.com
Classifier: Programming Language :: Python :: 3
Classifier: License :: OSI Approved :: MIT License
Classifier: Operating System :: OS Independent
Requires-Python: >=3.6
License-File: LICENSE
Requires-Dist: docx2pdf>=0.1.7
Dynamic: author
Dynamic: author-email
Dynamic: classifier
Dynamic: description
Dynamic: description-content-type
Dynamic: license-file
Dynamic: requires-dist
Dynamic: requires-python
Dynamic: summary
